easyfig/__init__.py
easyfig/main.py
easyfig-2.5.0.dist-info/LICENSE
easyfig-2.5.0.dist-info/METADATA
easyfig-2.5.0.dist-info/WHEEL
easyfig-2.5.0.dist-info/entry_points.txt
easyfig-2.5.0.dist-info/top_level.txt
easyfig-2.5.0.dist-info/RECORD
