Metadata-Version: 2.2
Name: easyfig
Version: 2.5.0
Summary: A simple simulation plotting tool with GUI. 适合科研人员的Python快速仿真绘图工具版本！A Python tool for researchers to create figures for academic papers!
Home-page: https://github.com/Jesse-tien/Easyfig
Author: Yu-Xin Tian
Author-email: neu.tianyuxin.2013@gmail.com
Classifier: Programming Language :: Python :: 3
Classifier: Operating System :: OS Independent
Requires-Python: >=3.8
License-File: LICENSE
Requires-Dist: numpy
Requires-Dist: sympy
Requires-Dist: matplotlib
Requires-Dist: ipython
Requires-Dist: notebook
Requires-Dist: pyperclip
Requires-Dist: qrcode
Dynamic: author
Dynamic: author-email
Dynamic: classifier
Dynamic: description
Dynamic: description-content-type
Dynamic: home-page
Dynamic: requires-dist
Dynamic: requires-python
Dynamic: summary
